agentX/__init__.py
agentX/agent_x.py
example/__init__.py
example/simple_agent.py
xAI/__init__.py
xAI/x_ai.py
agentxai-0.1.5.dist-info/LICENSE
agentxai-0.1.5.dist-info/METADATA
agentxai-0.1.5.dist-info/WHEEL
agentxai-0.1.5.dist-info/top_level.txt
agentxai-0.1.5.dist-info/RECORD
