Metadata-Version: 2.1
Name: agentxai
Version: 0.1.5
Summary: An agent that uses XAI to achieve goals by executing tools
Home-page: https://github.com/wickthumb/agentX
Author: wickthumb
Author-email: steven@wick3d.llc
Classifier: Development Status :: 3 - Alpha
Classifier: Intended Audience :: Developers
Classifier: License :: OSI Approved :: MIT License
Classifier: Programming Language :: Python :: 3
Classifier: Programming Language :: Python :: 3.6
Classifier: Programming Language :: Python :: 3.7
Classifier: Programming Language :: Python :: 3.8
Classifier: Programming Language :: Python :: 3.9
Requires-Python: >=3.6
License-File: LICENSE
Requires-Dist: annotated-types==0.7.0
Requires-Dist: anyio==4.6.2.post1
Requires-Dist: build==1.2.2.post1
Requires-Dist: certifi==2024.8.30
Requires-Dist: charset-normalizer==3.4.0
Requires-Dist: distro==1.9.0
Requires-Dist: docutils==0.21.2
Requires-Dist: h11==0.14.0
Requires-Dist: httpcore==1.0.7
Requires-Dist: httpx==0.27.2
Requires-Dist: idna==3.10
Requires-Dist: importlib_metadata==8.5.0
Requires-Dist: jaraco.classes==3.4.0
Requires-Dist: jaraco.context==6.0.1
Requires-Dist: jaraco.functools==4.1.0
Requires-Dist: jiter==0.7.1
Requires-Dist: keyring==25.5.0
Requires-Dist: markdown-it-py==3.0.0
Requires-Dist: mdurl==0.1.2
Requires-Dist: more-itertools==10.5.0
Requires-Dist: nh3==0.2.18
Requires-Dist: openai==1.55.0
Requires-Dist: packaging==24.2
Requires-Dist: pkginfo==1.10.0
Requires-Dist: pydantic==2.10.1
Requires-Dist: pydantic_core==2.27.1
Requires-Dist: Pygments==2.18.0
Requires-Dist: pyproject_hooks==1.2.0
Requires-Dist: python-dotenv==1.0.1
Requires-Dist: readme_renderer==44.0
Requires-Dist: requests==2.32.3
Requires-Dist: requests-toolbelt==1.0.0
Requires-Dist: rfc3986==2.0.0
Requires-Dist: rich==13.9.4
Requires-Dist: setuptools==75.6.0
Requires-Dist: sniffio==1.3.1
Requires-Dist: tenacity==9.0.0
Requires-Dist: tqdm==4.67.0
Requires-Dist: twine==5.1.1
Requires-Dist: typing_extensions==4.12.2
Requires-Dist: urllib3==2.2.3
Requires-Dist: zipp==3.21.0
